Quizlet_API-0.1.0.dist-info/DESCRIPTION.rst
Quizlet_API-0.1.0.dist-info/METADATA
Quizlet_API-0.1.0.dist-info/RECORD
Quizlet_API-0.1.0.dist-info/WHEEL
Quizlet_API-0.1.0.dist-info/metadata.json
Quizlet_API-0.1.0.dist-info/top_level.txt
quizlet/__init__.py
quizlet/client.py
quizlet/entities.py
