Metadata-Version: 2.0
Name: Quizlet-API
Version: 0.1.0
Summary: Python wrapper for Quizlet HTTP API.
Home-page: https://github.com/Answerky/quizlet-python
Author: Answerky
Author-email: pipy@answer,ky
License: UNKNOWN
Platform: UNKNOWN
Requires-Dist: requests
Requires-Dist: tortilla
